LICENSE
MANIFEST.in
requirements.txt
setup.py
anadama2/__init__.py
anadama2/backends.py
anadama2/cli.py
anadama2/document.py
anadama2/helpers.py
anadama2/picklerunner.py
anadama2/reporters.py
anadama2/runners.py
anadama2/taskcontainer.py
anadama2/temp.py
anadama2/tool.py
anadama2/tracked.py
anadama2/workflow.py
anadama2.egg-info/PKG-INFO
anadama2.egg-info/SOURCES.txt
anadama2.egg-info/dependency_links.txt
anadama2.egg-info/entry_points.txt
anadama2.egg-info/not-zip-safe
anadama2.egg-info/requires.txt
anadama2.egg-info/top_level.txt
anadama2/grid/__init__.py
anadama2/grid/aws.py
anadama2/grid/aws_batch_task.py
anadama2/grid/grid.py
anadama2/grid/sge.py
anadama2/grid/slurm.py
anadama2/util/__init__.py
anadama2/util/auth.py
anadama2/util/filespec.py
anadama2/util/fname.py
anadama2/util/matcher.py
examples/.gitignore
examples/download_files.py
examples/exe_check.py
examples/has_a_function.py
examples/kneaddata_workflow.py
examples/kvcontainer.py
examples/simple.py
examples/jupyter_notebooks/AnADAMA2_download_files_example.ipynb
examples/jupyter_notebooks/AnADAMA2_shotgun_workflow_example.ipynb
examples/tutorial/sample1.fastq
examples/tutorial/sample2.fastq