Metadata-Version: 1.1
Name: anadama2
Version: 0.8.0
Summary: AnADAMA2: Another Automated Data Analysis Management Application 2
Home-page: http://huttenhower.sph.harvard.edu/anadama2
Author: AnADAMA2 Development Team
Author-email: anadama-users@googlegroups.com
License: MIT
Keywords: microbial,microbiome,bioinformatics,workflow,grid,anadama,anadama2
Platform: Linux
Platform: MacOS
Classifier: Programming Language :: Python
Classifier: Development Status :: 5 - Production/Stable
Classifier: Environment :: Console
Classifier: Operating System :: MacOS
Classifier: Operating System :: Unix
Classifier: Programming Language :: Python :: 2.7
Classifier: Programming Language :: Python :: 3.4
Classifier: Topic :: Scientific/Engineering :: Bio-Informatics
